cangjie_mcp/__init__.py
cangjie_mcp/__main__.py
cangjie_mcp/cli.py
cangjie_mcp/cli_args.py
cangjie_mcp/config.py
cangjie_mcp/context.py
cangjie_mcp/defaults.py
cangjie_mcp/factory.py
cangjie_mcp/py.typed
cangjie_mcp/utils.py
cangjie_mcp/indexer/__init__.py
cangjie_mcp/indexer/api_extractor.py
cangjie_mcp/indexer/chunker.py
cangjie_mcp/indexer/document_source.py
cangjie_mcp/indexer/embeddings.py
cangjie_mcp/indexer/initializer.py
cangjie_mcp/indexer/loader.py
cangjie_mcp/indexer/reranker.py
cangjie_mcp/indexer/store.py
cangjie_mcp/lsp/__init__.py
cangjie_mcp/lsp/cli.py
cangjie_mcp/lsp/client.py
cangjie_mcp/lsp/config.py
cangjie_mcp/lsp/dependency.py
cangjie_mcp/lsp/tools.py
cangjie_mcp/lsp/types.py
cangjie_mcp/lsp/utils.py
cangjie_mcp/prebuilt/__init__.py
cangjie_mcp/prebuilt/manager.py
cangjie_mcp/prompts/__init__.py
cangjie_mcp/prompts/docs.txt
cangjie_mcp/prompts/lsp.txt
cangjie_mcp/repo/__init__.py
cangjie_mcp/repo/git_manager.py
cangjie_mcp/server/__init__.py
cangjie_mcp/server/app.py
cangjie_mcp/server/combined_app.py
cangjie_mcp/server/lsp_app.py
cangjie_mcp/server/tools.py
cangjie_mcp-0.2.1.dist-info/METADATA
cangjie_mcp-0.2.1.dist-info/WHEEL
cangjie_mcp-0.2.1.dist-info/entry_points.txt
cangjie_mcp-0.2.1.dist-info/licenses/LICENSE
cangjie_mcp-0.2.1.dist-info/RECORD
