Metadata-Version: 2.4
Name: cangjie-mcp
Version: 0.2.1
Summary: MCP server for Cangjie programming language documentation
Project-URL: Homepage, https://github.com/Zxilly/cangjie-mcp
Project-URL: Repository, https://github.com/Zxilly/cangjie-mcp
Project-URL: Issues, https://github.com/Zxilly/cangjie-mcp/issues
Author-email: Zxilly <zxilly@outlook.com>
License: MIT
License-File: LICENSE
Keywords: ai,cangjie,documentation,embeddings,llm,mcp,model-context-protocol,rag,vector-search
Classifier: Development Status :: 4 - Beta
Classifier: Intended Audience :: Developers
Classifier: License :: OSI Approved :: MIT License
Classifier: Operating System :: OS Independent
Classifier: Programming Language :: Python :: 3
Classifier: Programming Language :: Python :: 3.13
Classifier: Topic :: Scientific/Engineering :: Artificial Intelligence
Classifier: Topic :: Software Development :: Documentation
Classifier: Typing :: Typed
Requires-Python: >=3.13
Requires-Dist: chromadb>=1.4.0
Requires-Dist: gitpython>=3.1.46
Requires-Dist: httpx>=0.28.0
Requires-Dist: llama-index-core>=0.14.0
Requires-Dist: llama-index-embeddings-huggingface>=0.6.0
Requires-Dist: llama-index-embeddings-openai-like>=0.2.2
Requires-Dist: llama-index-embeddings-openai>=0.5.0
Requires-Dist: llama-index-vector-stores-chroma>=0.5.0
Requires-Dist: mcp[cli]>=1.25.0
Requires-Dist: pydantic-settings>=2.12.0
Requires-Dist: pydantic>=2.12.0
Requires-Dist: rich>=14.2.0
Requires-Dist: sentence-transformers>=5.2.0
Requires-Dist: typer>=0.21.0
